{
  "version": 1,
  "at": "2026-07-22T16:41:52.275Z",
  "base": "https://meridian-backend-ikx8.onrender.com",
  "results": {
    "/healthz": {
      "status": 200,
      "ok": true,
      "body": "{\"ok\":true,\"service\":\"ember-runtime\",\"children\":{\"observer\":true,\"payday\":true,\"sentinel\":true}}"
    },
    "/readyz": {
      "status": 200,
      "ok": true,
      "body": "{\"ready\":true,\"service\":\"ember-runtime\",\"children\":{\"observer\":true,\"payday\":true,\"sentinel\":true}}"
    },
    "/status": {
      "status": 200,
      "ok": true,
      "body": "{\"ready\":true,\"continuityAddress\":\"0x068bB96e849F0DE3D49944Ec0F4aEd3D6B165770\",\"missionStartAt\":1784683614}"
    },
    "/metrics": {
      "status": 200,
      "ok": true,
      "body": "ember_sentinel_configured 1\nember_sentinel_checks_total 4\nember_sentinel_check_failures_total 0\nember_sentinel_rescues_total 0\n"
    },
    "/observer/healthz": {
      "status": 200,
      "ok": true,
      "body": "{\"ok\":true,\"service\":\"primary-observer\"}"
    },
    "/payday/healthz": {
      "status": 200,
      "ok": true,
      "body": "{\"ok\":true,\"service\":\"payday\"}"
    },
    "/sentinel/healthz": {
      "status": 200,
      "ok": true,
      "body": "{\"ok\":true,\"service\":\"sentinel\"}"
    },
    "unauth/check": {
      "status": 401
    },
    "unauth/rescue": {
      "status": 401
    },
    "unauth/v1/executions": {
      "status": 401
    },
    "hmacCheck": {
      "status": 200,
      "body": {
        "missionId": "1",
        "continuityAddress": "0x068bB96e849F0DE3D49944Ec0F4aEd3D6B165770",
        "checkedAt": "2026-07-22T16:41:52.298Z",
        "executionSampleSize": 50,
        "receiptVerifiedPayments": 50,
        "receiptBacked": true,
        "state": "MISSION_DOWN",
        "reason": "missed_beyond_grace",
        "expectedSlotCount": 183,
        "paidSlotCount": 50,
        "missedSlots": [
          1784683614,
          1784683914,
          1784684214,
          1784684514,
          1784684814,
          1784685114,
          1784685414,
          1784685714,
          1784686014,
          1784686314,
          1784686614,
          1784686914,
          1784687214,
          1784687514,
          1784687814,
          1784688114,
          1784688414,
          1784688714,
          1784689014,
          1784689314,
          1784689614,
          1784689914,
          1784690214,
          1784690514,
          1784690814,
          1784691114,
          1784691414,
          1784691714,
          1784692014,
          1784692314,
          1784692614,
          1784692914,
          1784693214,
          1784693514,
          1784693814,
          1784694114,
          1784694414,
          1784694714,
          1784695014,
          1784695314,
          1784695614,
          1784695914,
          1784696214,
          1784696514,
          1784696814,
          1784697114,
          1784697414,
          1784697714,
          1784698014,
          1784698314,
          1784698614,
          1784698914,
          1784699214,
          1784699514,
          1784699814,
          1784700114,
          1784700414,
          1784700714,
          1784701014,
          1784701314,
          1784701614,
          1784701914,
          1784702214,
          1784702514,
          1784702814,
          1784703114,
          1784703414,
          1784703714,
          1784704014,
          1784704314,
          1784704614,
          1784704914,
          1784705214,
          1784705514,
          1784705814,
          1784706114,
          1784706414,
          1784706714,
          1784707014,
          1784707314,
          1784707614,
          1784707914,
          1784708214,
          1784708514,
          1784708814,
          1784709114,
          1784709414,
          1784709714,
          1784710014,
          1784710314,
          1784710614,
          1784710914,
          1784711214,
          1784711514,
          1784711814,
          1784712114,
          1784712414,
          1784712714,
          1784713014,
          1784713314,
          1784713614,
          1784713914,
          1784714214,
          1784714514,
          1784714814,
          1784715114,
          1784715414,
          1784715714,
          1784716014,
          1784716314,
          1784716614,
          1784716914,
          1784717214,
          1784717514,
          1784717814,
          1784718114,
          1784718414,
          1784718714,
          1784719014,
          1784719314,
          1784719614,
          1784719914,
          1784720214,
          1784720514,
          1784720814,
          1784721114,
          1784721414,
          1784721714,
          1784722014,
          1784722314,
          1784722614,
          1784722914,
          1784725314
        ],
        "latestPaidSlot": 1784738214
      }
    }
  },
  "pass": true
}
